guillotina_mailer/__init__.py
guillotina_mailer/api.py
guillotina_mailer/configure.zcml
guillotina_mailer/encoding.py
guillotina_mailer/exceptions.py
guillotina_mailer/interfaces.py
guillotina_mailer/utility.py
guillotina_mailer-1.1.2.dist-info/METADATA
guillotina_mailer-1.1.2.dist-info/RECORD
guillotina_mailer-1.1.2.dist-info/WHEEL
guillotina_mailer-1.1.2.dist-info/top_level.txt
guillotina_mailer-1.1.2.dist-info/zip-safe
