Metadata-Version: 2.1
Name: guillotina-mailer
Version: 1.1.2
Summary: Mailer integration with guillotina
Home-page: https://github.com/pyrenees/guillotina_mailer
Author: Nathan Van Gheem
Author-email: nathan.vangheem@wildcardcorp.com
License: BSD
Keywords: async mail guillotina
Platform: UNKNOWN
Classifier: Programming Language :: Python :: 3.5
Classifier: Programming Language :: Python :: 3.6
Classifier: Topic :: Software Development :: Libraries :: Python Modules
Requires-Dist: setuptools
Requires-Dist: guillotina
Requires-Dist: html2text
Requires-Dist: aiosmtplib
